adarsh/__init__.py
adarsh/follow_bot.py
adarsh/spotiboost.py
spotiboost-3.7.1.dist-info/METADATA
spotiboost-3.7.1.dist-info/WHEEL
spotiboost-3.7.1.dist-info/entry_points.txt
spotiboost-3.7.1.dist-info/top_level.txt
spotiboost-3.7.1.dist-info/RECORD
