Metadata-Version: 2.1
Name: spotiboost
Version: 3.7.1
Summary: A free and open-source spotify followers increaser package
Home-page: https://github.com/adarsh-goel/spotiboost
Author: Adarsh Goel
Author-email: contact@adarsh.codes
License: GPL
Classifier: Development Status :: 4 - Beta
Classifier: Intended Audience :: Developers
Classifier: Topic :: Software Development :: Libraries :: Python Modules
Classifier: License :: OSI Approved :: GNU General Public License v3 (GPLv3)
Classifier: Programming Language :: Python :: 3
Classifier: Operating System :: OS Independent
Classifier: Environment :: Console
Requires-Python: >=3.5
Requires-Dist: requests (==2.27.1)
